{"data":{"_id":2000,"properties":{"status":{"name":"status","kind":"scalar","type":"string","getter":false,"setter":false,"array":false,"runtimeType":"EMasterMandateStatusEnum"},"timestamp":{"name":"timestamp","kind":"scalar","type":"Date","getter":false,"setter":false,"array":false,"runtimeType":"Date"}},"primaryKeys":[],"filters":{},"hooks":{},"indexes":[],"uniques":[],"className":"MandateStatusHistory","path":"./entities/mandate.entity.ts","name":"MandateStatusHistory","embeddable":true,"abstract":false,"internal":true,"constructorParams":[],"toJsonParams":[],"useCache":true,"collection":"mandate_status_history"},"origin":"./entities/mandate.entity.ts","hash":"b572629e2af3c17ec366228a7b695360","version":"6.4.0"}
